basketball_reference_webscrapper/__init__.py
basketball_reference_webscrapper/constants/__init__.py
basketball_reference_webscrapper/constants/team_city_refdata.csv
basketball_reference_webscrapper/constants/team_season_validity.yaml
basketball_reference_webscrapper/data_models/__init_.py
basketball_reference_webscrapper/data_models/feature_model.py
basketball_reference_webscrapper/params.yaml
basketball_reference_webscrapper/utils/__init__.py
basketball_reference_webscrapper/utils/logs.py
basketball_reference_webscrapper/utils/team_utils.py
basketball_reference_webscrapper/web_scrap_basketball_reference.py
basketball_reference_webscrapper/web_scrap_nba_api.py
basketball_reference_webscrapper/web_scrap_player_boxscore_nba_api.py
basketball_reference_webscrapper-0.7.4.dist-info/METADATA
basketball_reference_webscrapper-0.7.4.dist-info/WHEEL
basketball_reference_webscrapper-0.7.4.dist-info/RECORD
