Metadata-Version: 2.4
Name: basketball-reference-webscrapper
Version: 0.7.4
Summary: Python package for Basketball Reference that gathers data by scraping the website
Author: Yannick Flores
Author-email: yannick.flores1992@gmail.com
Requires-Python: >=3.11,<4.0
Classifier: Programming Language :: Python :: 3
Classifier: Programming Language :: Python :: 3.11
Classifier: Programming Language :: Python :: 3.12
Classifier: Programming Language :: Python :: 3.13
Classifier: Programming Language :: Python :: 3.14
Requires-Dist: beautifulsoup4 (==4.12.*)
Requires-Dist: nba-api (==1.10.*)
Requires-Dist: numpy (==2.1.*)
Requires-Dist: pandas (==2.2.*)
Requires-Dist: pydantic (>=2.6.1,<3.0.0)
Requires-Dist: pylint (>=2.15.10,<3.0.0)
Requires-Dist: pytest
Requires-Dist: requests (==2.32.*)
